reticulum/__init__.py
reticulum/__main__.py
reticulum/cli.py
reticulum/dependency_analyzer.py
reticulum/dockerfile_analyzer.py
reticulum/exposure_analyzer.py
reticulum/main.py
reticulum/mermaid_builder.py
reticulum/path_consolidator.py
reticulum-4.1.2.dist-info/METADATA
reticulum-4.1.2.dist-info/WHEEL
reticulum-4.1.2.dist-info/entry_points.txt
reticulum-4.1.2.dist-info/RECORD
