Metadata-Version: 2.3
Name: reticulum
Version: 4.1.2
Summary: Exposure Scanner for Cloud Infrastructure Security Analysis
License: MIT
Keywords: security,kubernetes,helm,devsecops,cloud,exposure,analysis
Author: Jose Palanco
Author-email: jose.palanco@plexicus.ai
Requires-Python: >=3.9,<4.0
Classifier: Development Status :: 4 - Beta
Classifier: Intended Audience :: Developers
Classifier: Intended Audience :: System Administrators
Classifier: License :: OSI Approved :: MIT License
Classifier: Operating System :: OS Independent
Classifier: Programming Language :: Python :: 3
Classifier: Programming Language :: Python :: 3.9
Classifier: Programming Language :: Python :: 3.10
Classifier: Programming Language :: Python :: 3.11
Classifier: Programming Language :: Python :: 3.12
Classifier: Programming Language :: Python :: 3.13
Classifier: Topic :: Security
Classifier: Topic :: Software Development :: Libraries :: Python Modules
Classifier: Topic :: System :: Systems Administration
Requires-Dist: pyyaml (>=6.0,<7.0)
Project-URL: Homepage, https://github.com/plexicus/reticulum
Project-URL: Repository, https://github.com/plexicus/reticulum
